header_filter/__init__.py
header_filter/decorator.py
header_filter/matchers.py
header_filter/middleware.py
header_filter/rules.py
django_header_filter-0.1.0.dist-info/LICENSE
django_header_filter-0.1.0.dist-info/METADATA
django_header_filter-0.1.0.dist-info/WHEEL
django_header_filter-0.1.0.dist-info/top_level.txt
django_header_filter-0.1.0.dist-info/RECORD
